anuvaad_auditor/__init__.py
anuvaad_auditor/config.py
anuvaad_auditor/errorhandler.py
anuvaad_auditor/eswrapper.py
anuvaad_auditor/kfproducer.py
anuvaad_auditor/loghandler.py
anuvaadAauditor-1.0.0.dist-info/LICENSE
anuvaadAauditor-1.0.0.dist-info/METADATA
anuvaadAauditor-1.0.0.dist-info/WHEEL
anuvaadAauditor-1.0.0.dist-info/top_level.txt
anuvaadAauditor-1.0.0.dist-info/RECORD
