Metadata-Version: 2.1
Name: anuvaadAauditor
Version: 1.0.0
Summary: A package to standardize and manage audit details and errors in anuvaad dataflow pipeline
Home-page: https://www.tarento.com
Download-URL: https://github.com/project-anuvaad/anuvaad-em/archive/16.0.0.tar.gz
Author: Vishal Mahuli
Author-email: vishal.mahuli@tarento.com
License: MIT
Keywords: ANUVAAD,ERROR,MANAGER,TARENTO,EKSTEP,SUVAAS,AUDIT,LOG,INDEX
Classifier: Development Status :: 4 - Beta
Classifier: Intended Audience :: Developers
Classifier: Topic :: Software Development :: Build Tools
Classifier: License :: OSI Approved :: MIT License
Classifier: Programming Language :: Python :: 3.7
License-File: LICENSE
Requires-Dist: kafka-python
Requires-Dist: uuid
Requires-Dist: datetime
Requires-Dist: elasticsearch
